nbformat_cli/__init__.py
nbformat_cli/__main__.py
nbformat_cli-0.1.0.dist-info/METADATA
nbformat_cli-0.1.0.dist-info/WHEEL
nbformat_cli-0.1.0.dist-info/entry_points.txt
nbformat_cli-0.1.0.dist-info/RECORD
